pynlopol/__init__.py
pynlopol/class_chi.py
pynlopol/contract_tensor.py
pynlopol/dataio.py
pynlopol/expand_tensor.py
pynlopol/fitconfig.py
pynlopol/fitdata.py
pynlopol/fitdata_base.py
pynlopol/gen_pol_state_sequence.py
pynlopol/imgfitconfig.py
pynlopol/imgfitdata.py
pynlopol/nsmp.py
pynlopol/nsmp_common.py
pynlopol/nsmp_fit.py
pynlopol/nsmp_ref.py
pynlopol/nsmp_sim-Sirius.py
pynlopol/nsmp_sim.py
pynlopol/plot.py
pynlopol/polarimetry.py
pynlopol/report.py
pynlopol/verify_pol_state_sequence.py
pynlopol-1.1.0.data/data/scripts/fit_pipo_1point.py
pynlopol-1.1.0.data/data/scripts/fit_pipo_1point_zcq.py
pynlopol-1.1.0.data/data/scripts/fit_pipo_img.py
pynlopol-1.1.0.data/data/scripts/gen_pol_state_sequence.py
pynlopol-1.1.0.data/data/scripts/make_nsmp_tiff.py
pynlopol-1.1.0.data/data/scripts/pipo_check_c6v.py
pynlopol-1.1.0.data/data/scripts/plot_pipo_fit.py
pynlopol-1.1.0.data/data/scripts/plot_pipo_fit_map.py
pynlopol-1.1.0.data/data/scripts/plot_piponator_fit.py
pynlopol-1.1.0.data/data/scripts/show_pipo.py
pynlopol-1.1.0.data/data/scripts/sim_collagen_anim.py
pynlopol-1.1.0.data/data/scripts/sim_pipo.py
pynlopol-1.1.0.data/data/scripts/sim_pipo_collagen.bat
pynlopol-1.1.0.data/data/scripts/sim_pipo_collagen_hr.bat
pynlopol-1.1.0.data/data/scripts/sim_pipo_rtt.py
pynlopol-1.1.0.data/data/scripts/sim_pipo_zcq.bat
pynlopol-1.1.0.data/data/scripts/sim_pipo_zcq_hr.bat
pynlopol-1.1.0.data/data/scripts/sim_thg_c6v_anim.py
pynlopol-1.1.0.data/data/scripts/sim_zcq_pipo_anim.py
pynlopol-1.1.0.data/data/scripts/verify_pol_state_sequence.py
pynlopol-1.1.0.data/data/tests/pipo_8x8_pol_states.dat
pynlopol-1.1.0.data/data/tests/run_thg_c6v_pipo_fit_test.py
pynlopol-1.1.0.data/data/tests/test_polarimetry_fit.py
pynlopol-1.1.0.data/data/tests/test_polarimetry_lin.py
pynlopol-1.1.0.data/data/tests/test_polarimetry_nl.py
pynlopol-1.1.0.data/data/tests/test_polarimetry_plot.py
pynlopol-1.1.0.dist-info/METADATA
pynlopol-1.1.0.dist-info/WHEEL
pynlopol-1.1.0.dist-info/top_level.txt
pynlopol-1.1.0.dist-info/RECORD
