Metadata-Version: 2.1
Name: pynlopol
Version: 1.1.0
Summary: A Python library for nonlinear polarimetry.
Home-page: https://github.com/lukaskontenis/pynlopol
Author: Lukas Kontenis
Author-email: dse.ssd@gmail.com
Classifier: Programming Language :: Python :: 3
Classifier: License :: OSI Approved :: BSD License
Classifier: Operating System :: OS Independent
Requires-Python: >=3.6
Requires-Dist: numpy >=1.19.5
Requires-Dist: matplotlib >=3.3.3
Requires-Dist: scipy >=1.5.4
Requires-Dist: imageio >=2.9.0
Requires-Dist: pynlomic >=1.1.0
Requires-Dist: lkcom >=0.4.0
